mastermind/__init__.py
mastermind/tools.py
mastermind/utils.py
mastermind/prompts/mastermind.md
mastermind/prompts/test.md
mastermind_agent-0.7.0.dist-info/licenses/LICENSE
mastermind_agent-0.7.0.dist-info/METADATA
mastermind_agent-0.7.0.dist-info/WHEEL
mastermind_agent-0.7.0.dist-info/entry_points.txt
mastermind_agent-0.7.0.dist-info/top_level.txt
mastermind_agent-0.7.0.dist-info/RECORD
