Metadata-Version: 2.4
Name: mastermind-agent
Version: 0.7.0
Summary: Offensive CyberSecurity Agent
Author-email: Du Mingzhe <mingzhe@nus.edu.sg>
Requires-Python: >=3.11
License-File: LICENSE
Requires-Dist: rich>=13.0.0
Requires-Dist: python-dotenv>=1.0.0
Requires-Dist: langchain>=0.1.0
Requires-Dist: langchain-openai>=0.0.1
Requires-Dist: langchain-anthropic>=0.0.1
Requires-Dist: langchain-google-genai>=0.0.1
Requires-Dist: tavily-python>=0.3.0
Dynamic: license-file
